{
    "id": "1171119279",
    "title": "132 - Cancer Risk Reduction Strategies in the Context of Bariatric Surgery and Endoscopy",
    "description": "Chairs:\nProf Ariel Ortiz Lagardere (USA/Mexico) \nDr Ben Clapp (USA)\n\nModerators\nProf Georges Al Hajj (Lebanon) \nDr Geri Keane (USA)\nDr Zdenko Boras (Croatia) \n\nBreast Cancer Risk after Bariatric Surgery & Implications of Type of Bariatric Surgery\nDr Reynu Rajan (Malaysia) \n\nShould there be a Preferred Bariatric Surgery Operation to Maximise Cancer Risk Reduction Strategy from Weight Loss?\nProf Ali Aminian (USA) \n\nEndoscopic Treatments for Barrett\u2019s Oesophagus & applications for Barrett\u2019s Oesophagus Post-Sleeve Gastrectomy \nProf Manoel Galvao Neto (USA) \n\nEndoscopic Weight Loss Strategies for Severely Obese Patients with Familial Adenomatous Polyposis Coli  \nProf Roberto Simons-Linares (USA)",
    "duration": 5297,
    "thumbnail": "https://i.vimeocdn.com/video/2130512929-f5bc11c88817b7050e8bb0de002d6f9d70c67c77747b4e9efc879812afc50761-d?region=us",
    "publish_date": "2026-03-06"
}